formly/__init__.py
formly/auth_backend.py
formly/callbacks.py
formly/conf.py
formly/fields.py
formly/hooks.py
formly/models.py
formly/receivers.py
formly/urls.py
formly/utils.py
formly/forms/__init__.py
formly/forms/design.py
formly/forms/run.py
formly/forms/widgets.py
formly/migrations/0001_initial.py
formly/migrations/0002_add_expected_answers.py
formly/migrations/0003_auto_20160816_2022.py
formly/migrations/0004_auto_20161206_1401.py
formly/migrations/0005_field_scale.py
formly/migrations/0006_auto_20161206_1415.py
formly/migrations/0007_help_text_and_label_to_textfield.py
formly/migrations/0008_auto_20170609_0800.py
formly/migrations/0009_ordinalscale_kind.py
formly/migrations/0010_auto_20170609_0800.py
formly/migrations/0011_field_mapping.py
formly/migrations/0012_fix_multi_text_answer_data.py
formly/migrations/__init__.py
formly/templatetags/__init__.py
formly/templatetags/formly.py
formly/tests/__init__.py
formly/tests/factories.py
formly/tests/mixins.py
formly/tests/models.py
formly/tests/test_forms.py
formly/tests/test_models.py
formly/tests/test_views.py
formly/tests/tests.py
formly/tests/urls.py
formly/utils/__init__.py
formly/utils/importing.py
formly/utils/remapping.py
formly/utils/views.py
formly/views/__init__.py
formly/views/design.py
formly/views/results.py
formly/views/run.py
formly-3.0.0.dist-info/AUTHORS
formly-3.0.0.dist-info/LICENSE
formly-3.0.0.dist-info/METADATA
formly-3.0.0.dist-info/WHEEL
formly-3.0.0.dist-info/top_level.txt
formly-3.0.0.dist-info/RECORD
