Metadata-Version: 2.1
Name: formly
Version: 3.0.0
Summary: A forms/survey generator for dynamically constructed multi-page surveys
Home-page: http://github.com/eldarion/formly/
Author: Patrick Altman
Author-email: paltman@eldarion.com
License: BSD
Platform: UNKNOWN
Classifier: Development Status :: 5 - Production/Stable
Classifier: Environment :: Web Environment
Classifier: Framework :: Django
Classifier: Framework :: Django :: 2.2
Classifier: Framework :: Django :: 3.1
Classifier: Intended Audience :: Developers
Classifier: License :: OSI Approved :: BSD License
Classifier: Operating System :: OS Independent
Classifier: Programming Language :: Python
Classifier: Programming Language :: Python :: 3
Classifier: Programming Language :: Python :: 3.6
Classifier: Topic :: Software Development :: Libraries :: Python Modules
Requires-Dist: django (>=1.11)
Requires-Dist: django-appconf (>=1.0.2)
Requires-Dist: jsonfield (>=2.0.2)
Requires-Dist: six (>=1.15.0)
